viafoundry/__init__.py
viafoundry/auth.py
viafoundry/bin/__init__.py
viafoundry/bin/foundry.py
viafoundry/client.py
viafoundry/metadata.py
viafoundry/models/domain/metadata.py
viafoundry/models/domain/process.py
viafoundry/models/domain/reports.py
viafoundry/process.py
viafoundry/reports.py
viafoundry/utils.py
viafoundry_sdk-1.0.25.dist-info/METADATA
viafoundry_sdk-1.0.25.dist-info/WHEEL
viafoundry_sdk-1.0.25.dist-info/entry_points.txt
viafoundry_sdk-1.0.25.dist-info/RECORD
