Metadata-Version: 2.3
Name: viafoundry_sdk
Version: 1.0.25
Summary: A Python SDK and CLI tool for interacting with ViaFoundry APIs.
License: MIT
Author: Alper Kucukural
Author-email: alper@viascientific.com
Requires-Python: >=3.9
Classifier: Development Status :: 4 - Beta
Classifier: Intended Audience :: Developers
Classifier: License :: OSI Approved :: MIT License
Classifier: Operating System :: OS Independent
Classifier: Programming Language :: Python :: 3
Classifier: Programming Language :: Python :: 3.9
Classifier: Programming Language :: Python :: 3.10
Classifier: Programming Language :: Python :: 3.11
Classifier: Programming Language :: Python :: 3.12
Classifier: Programming Language :: Python :: 3.13
Classifier: Topic :: Software Development :: Libraries :: Python Modules
Requires-Dist: click (>=8.0)
Requires-Dist: ipython (>=7.34.0,<8.0.0)
Requires-Dist: pandas (>=2.0.0,<3.0.0)
Requires-Dist: pydantic[email] (>=2.0)
Requires-Dist: requests (>=2.25.0)
Project-URL: Documentation, https://github.com/viascientific/viafoundry-sdk#readme
Project-URL: Homepage, https://github.com/viascienific/viafoundry-sdk
Project-URL: Issues, https://github.com/viascientific/viafoundry-sdk/issues
